COPYING
MANIFEST.in
README.rst
setup.py
examples/__init__.py
examples/bf.py
examples/emit-alphabet.bf
examples/square.py
examples/sum_of_squares.py
gccjit/__init__.py
gccjit/gccjit.pxd
gccjit/gccjit.pyx
gccjit.egg-info/PKG-INFO
gccjit.egg-info/SOURCES.txt
gccjit.egg-info/dependency_links.txt
gccjit.egg-info/top_level.txt
tests/__init__.py
tests/test.py