Metadata-Version: 1.1
Name: gccjit
Version: 0.4
Summary: Python bindings for libgccjit
Home-page: https://github.com/davidmalcolm/pygccjit
Author: David Malcolm
Author-email: jit@gcc.gnu.org
License: GPL v3
Platform: UNKNOWN
Classifier: Development Status :: 3 - Alpha
Classifier: Intended Audience :: Developers
Classifier: License :: OSI Approved :: GNU General Public License v3 or later (GPLv3+)
Classifier: Programming Language :: Python
Classifier: Topic :: Software Development :: Libraries :: Python Modules
Classifier: Operating System :: Unix
Classifier: Programming Language :: Python :: 2
Classifier: Programming Language :: Python :: 3
